{
  "simulation_config": {
    "num_shards": 4,
    "consensus_algorithm": "PoW",
    "block_time": 10,
    "network_latency": 100,
    "iterations": 5
  },
  "transaction_stats": {
    "total": 15,
    "successful": 11,
    "success_rate": 0.7333333333333333,
    "transactions_per_step": 20,
    "cross_shard_transactions": {
      "total": 5,
      "successful": 5,
      "success_rate": 1.0
    }
  },
  "performance_stats": {
    "avg_throughput": 0.25,
    "avg_latency": 12.53125,
    "energy_consumption": 1547.53,
    "congestion_level": 0.01337672288704386
  },
  "module_stats": {
    "mad_rapid": {
      "optimized_tx_count": 8,
      "total_tx_processed": 17,
      "avg_optimization_time": 0,
      "congestion_prediction_accuracy": 0
    },
    "acsc": {
      "successful_tx_count": 0,
      "total_tx_processed": 0,
      "strategy_usage": {}
    }
  }
}